Workbook

Sheet Job Calculator
A1: Job Calculator
A4: THE JOB
A5: Product | B5: Harvest - Carpet
A6: Square feet | B6: 1000
A7: Cash discount % | B7: 0
A8: Price per sq ft | B8: {=IFERROR(INDEX(Pricing!$E$5:$E$11,MATCH(B5,Pricing!$A$5:$A$11,0)),0)} -> 7.65
A9: Cost per sq ft | B9: {=IFERROR(INDEX(Pricing!$D$5:$D$11,MATCH(B5,Pricing!$A$5:$A$11,0)),0)} -> 3.46
A10: Full price (before discount) | B10: =B6*B8 -> 7650
A11: Cash discount $ | B11: =B10*B7 -> 0
A12: Customer pays | B12: =B10-B11 -> 7650
A14: FREE UPGRADES
A15: Free Upgrade | B15: Quantity | C15: Retail Value | D15: Your Cost
A16: 5 1/4 Baseboard | B16: 400 | C16: {=B16*IFERROR(INDEX(Settings!$C$18:$C$30,MATCH(A16,Settings!$A$18:$A$30,0)),0)} -> 1800 | D16: {=B16*IFERROR(INDEX(Settings!$D$18:$D$30,MATCH(A16,Settings!$A$18:$A$30,0)),0)} -> 1464
A17: Pad upgrade (carpet) | B17: 0 | C17: {=B17*IFERROR(INDEX(Settings!$C$18:$C$30,MATCH(A17,Settings!$A$18:$A$30,0)),0)} -> 0 | D17: {=B17*IFERROR(INDEX(Settings!$D$18:$D$30,MATCH(A17,Settings!$A$18:$A$30,0)),0)} -> 0
A18: None | B18: 0 | C18: {=B18*IFERROR(INDEX(Settings!$C$18:$C$30,MATCH(A18,Settings!$A$18:$A$30,0)),0)} -> 0 | D18: {=B18*IFERROR(INDEX(Settings!$D$18:$D$30,MATCH(A18,Settings!$A$18:$A$30,0)),0)} -> 0
A19: Total free upgrades | C19: =SUM(C16:C18) -> 1800 | D19: =SUM(D16:D18) -> 1464
A21: COMMISSION
A22: Total discount (cash + freebie value) | B22: =IF(B10=0,0,(B11+C19)/B10) -> 0.23529412
A23: Approval needed? | B23: =IF(ROUND(B22,4)>Settings!$C$10,"YES - over 20%, owner must approve","No") -> YES - over 20%, owner must approve
A24: Commission rate | B24: =IF(ROUND(B22,4)<=Settings!$C$6,Settings!$B$6,IF(ROUND(B22,4)<=Settings!$C$7,Settings!$B$7,IF(ROUND(B22,4)<=Settings!$C$8,Settings!$B$8,IF(ROUND(B22,4)<=Settings!$C$9,Settings!$B$9,Settings!$B$10)))) -> 0.08
A25: Job cost (install + material) | B25: =B6*B9 -> 3460
A26: Freebie cost | B26: =D19 -> 1464
A27: Gross profit | B27: =B12-B25-B26 -> 2726
A28: Rep commission | B28: =B27*B24 -> 218.08
A29: Appointment fee | B29: =Settings!$B$13 -> 75
A30: Total rep pay | B30: =B28+B29 -> 293.08
A32: YOU KEEP (before ads & overhead) | B32: =B27-B30 -> 2432.92

Sheet Pricing
A1: Product Pricing (per sq ft)
A2: Yellow cells = your numbers. Everything else calculates.
A4: Product | B4: Install Cost | C4: Material Cost | D4: Total Cost | E4: Selling Price | F4: Margin | G4: Discount | H4: Discounted Price | I4: Discounted Margin
A5: Jaguar - Carpet | B5: 2.02 | C5: 1.11 | D5: =B5+C5 -> 3.13 | E5: 6.91 | F5: =(E5-D5)/E5 -> 0.54703329 | G5: 0.2 | H5: =E5*(1-G5) -> 5.528 | I5: =(H5-D5)/H5 -> 0.43379161
A6: Harvest - Carpet | B6: 2.02 | C6: 1.44 | D6: =B6+C6 -> 3.46 | E6: 7.65 | F6: =(E6-D6)/E6 -> 0.54771242 | G6: 0.2 | H6: =E6*(1-G6) -> 6.12 | I6: =(H6-D6)/H6 -> 0.43464052
A7: Resolve - Carpet | B7: 2.02 | C7: 1.78 | D7: =B7+C7 -> 3.8 | E7: 8.4 | F7: =(E7-D7)/E7 -> 0.54761905 | G7: 0.2 | H7: =E7*(1-G7) -> 6.72 | I7: =(H7-D7)/H7 -> 0.43452381
A8: Faculty - Carpet | B8: 2.02 | C8: 2 | D8: =B8+C8 -> 4.02 | E8: 8.89 | F8: =(E8-D8)/E8 -> 0.54780652 | G8: 0.2 | H8: =E8*(1-G8) -> 7.112 | I8: =(H8-D8)/H8 -> 0.43475816
A9: Alpine - Vinyl | B9: 2.96 | C9: 1.59 | D9: =B9+C9 -> 4.55 | E9: 8.88 | F9: =(E9-D9)/E9 -> 0.48761261 | G9: 0.2 | H9: =E9*(1-G9) -> 7.104 | I9: =(H9-D9)/H9 -> 0.35951577
A10: Montclair - Vinyl | B10: 2.96 | C10: 1.69 | D10: =B10+C10 -> 4.65 | E10: 9.98 | F10: =(E10-D10)/E10 -> 0.53406814 | G10: 0.2 | H10: =E10*(1-G10) -> 7.984 | I10: =(H10-D10)/H10 -> 0.41758517
A11: Citadel - Vinyl | B11: 2.96 | C11: 2.09 | D11: =B11+C11 -> 5.05 | E11: 10.48 | F11: =(E11-D11)/E11 -> 0.51812977 | G11: 0.2 | H11: =E11*(1-G11) -> 8.384 | I11: =(H11-D11)/H11 -> 0.39766221

Sheet Settings
A1: Commission & Freebie Settings
A4: Commission Tiers
A5: Total Discount (cash + freebies) | B5: Commission (% of gross profit) | C5: Max Discount
A6: No discount | B6: 0.16 | C6: 0
A7: Up to 5% | B7: 0.14 | C7: 0.05
A8: Up to 10% | B8: 0.12 | C8: 0.1
A9: Up to 15% | B9: 0.1 | C9: 0.15
A10: Up to 20% | B10: 0.08 | C10: 0.2
A11: Over 20% = needs owner approval
A13: Appointment fee | B13: 75
A15: Free Upgrade List
A16: EXAMPLE prices below. Replace the yellow cells with your real retail price and cost.
A17: Free Upgrade | B17: Charged Per | C17: Retail Price (per unit) | D17: Your Cost (per unit)
A18: None | C18: 0 | D18: 0
A19: 5 1/4 Baseboard | B19: Linear ft | C19: 4.5 | D19: =1.66+2 -> 3.66
A20: Pad upgrade (carpet) | B20: Sq ft | C20: 0.6 | D20: 0.3
A28: Add more upgrades in the blank rows below (up to row 30).
